checkout_sdk/__init__.py
checkout_sdk/api_client.py
checkout_sdk/authorization_type.py
checkout_sdk/checkout_api.py
checkout_sdk/checkout_apm_api.py
checkout_sdk/checkout_configuration.py
checkout_sdk/checkout_response.py
checkout_sdk/checkout_sdk.py
checkout_sdk/checkout_sdk_builder.py
checkout_sdk/client.py
checkout_sdk/default_http_client.py
checkout_sdk/default_keys_credentials.py
checkout_sdk/default_sdk.py
checkout_sdk/environment.py
checkout_sdk/environment_subdomain.py
checkout_sdk/exception.py
checkout_sdk/http_client_interface.py
checkout_sdk/http_metadata.py
checkout_sdk/json_serializer.py
checkout_sdk/oauth_access_token.py
checkout_sdk/oauth_credentials.py
checkout_sdk/oauth_scopes.py
checkout_sdk/oauth_sdk.py
checkout_sdk/platform_type.py
checkout_sdk/properties.py
checkout_sdk/sdk_authorization.py
checkout_sdk/sdk_credentials.py
checkout_sdk/static_keys_builder.py
checkout_sdk/utils.py
checkout_sdk/accounts/__init__.py
checkout_sdk/accounts/accounts.py
checkout_sdk/accounts/accounts_client.py
checkout_sdk/apm/__init__.py
checkout_sdk/apm/ideal_client.py
checkout_sdk/apm/klarna.py
checkout_sdk/apm/klarna_client.py
checkout_sdk/apm/sepa_client.py
checkout_sdk/balances/__init__.py
checkout_sdk/balances/balances.py
checkout_sdk/balances/balances_client.py
checkout_sdk/common/__init__.py
checkout_sdk/common/common.py
checkout_sdk/common/enums.py
checkout_sdk/customers/__init__.py
checkout_sdk/customers/customers.py
checkout_sdk/customers/customers_client.py
checkout_sdk/customers/customers_client_previous.py
checkout_sdk/disputes/__init__.py
checkout_sdk/disputes/disputes.py
checkout_sdk/disputes/disputes_client.py
checkout_sdk/events/__init__.py
checkout_sdk/events/events.py
checkout_sdk/events/events_client.py
checkout_sdk/files/__init__.py
checkout_sdk/files/files.py
checkout_sdk/files/files_client.py
checkout_sdk/financial/__init__.py
checkout_sdk/financial/financial.py
checkout_sdk/financial/financial_client.py
checkout_sdk/forex/__init__.py
checkout_sdk-3.4.4.dist-info/licenses/LICENSE.md
checkout_sdk-3.4.4.dist-info/METADATA
checkout_sdk-3.4.4.dist-info/WHEEL
checkout_sdk-3.4.4.dist-info/top_level.txt
checkout_sdk-3.4.4.dist-info/RECORD
